{"id": 6321, "title": "\u65af\u6d3e\u514b\u5c9b\u5192\u9669\u4e4b\u65c5\u2014\u2014\u81f4\u4e00\u7fa4\u8ff7\u5f1f\u7684\u9752\u6625", "url": "https://maoyan.com/films/329642", "img": "http://p0.meituan.net/movie/7a0f2180a8a5583c17f5121312d79db1300316.jpg@160w_220h_1e_1c", "ename": "Spike Island", "types": "\u5267\u60c5,\u97f3\u4e50", "body": "A rising indie band travels to Spike Island, Cheshire, in May of 1990 to see The Stone Roses.", "directors": "\u9a6c\u7279\u00b7\u6000\u514b\u6d1b\u65af", "actors": "\u827e\u7565\u7279\u00b7\u63d0\u7279\u6069\u7d22.\u5c3c\u514b\u00b7\u8fc8\u745e\u83b1\u683c\u4f26.Jordon Murphy.Adam Long"}